cval.py
cval-1.0.0.dist-info/LICENSE
cval-1.0.0.dist-info/METADATA
cval-1.0.0.dist-info/WHEEL
cval-1.0.0.dist-info/top_level.txt
cval-1.0.0.dist-info/RECORD
