Metadata-Version: 2.1
Name: cval
Version: 1.0.0
Summary: A layer of protection for pythons eval
Home-page: https://github.com/ZackeryRSmith/cval
Author: Zackery Smith
Author-email: zackery.smith82307@gmail.com
License: GNU GPL-3.0
Platform: UNKNOWN
Classifier: License :: OSI Approved :: GNU General Public License v3 (GPLv3)
Classifier: Programming Language :: Python
Classifier: Programming Language :: Python :: 3
Classifier: Programming Language :: Python :: 3.6
Classifier: Programming Language :: Python :: 3.9
Classifier: Programming Language :: Python :: 3.10
Requires-Python: >=3.0.0
License-File: LICENSE
